Metadata-Version: 2.4
Name: mcp-server-everything-search-fastmcp
Version: 0.2.2
Summary: A Model Context Protocol server providing fast file searching using Everything SDK
Project-URL: Homepage, https://github.com/fastmcp-me/mcp-everything-search#readme
Project-URL: Repository, https://github.com/fastmcp-me/mcp-everything-search.git
Project-URL: Issues, https://github.com/fastmcp-me/mcp-everything-search/issues
Author-email: Mamerto Fabian <aidrivencoder@gmail.com>
License: MIT License
License-File: LICENSE
Keywords: everything,llm,mcp,search
Classifier: Programming Language :: Python :: 3
Classifier: Programming Language :: Python :: 3.10
Requires-Python: >=3.10
Requires-Dist: mcp>=1.0.0
Requires-Dist: pydantic>=2.0.0
